ytdlp_gui-1.0.1.dist-info/licenses/LICENSE
ytdlpg/__main__.py
ytdlpg/main.py
ytdlpg/manager.py
ytdlpg/options.py
ytdlp_gui-1.0.1.dist-info/METADATA
ytdlp_gui-1.0.1.dist-info/WHEEL
ytdlp_gui-1.0.1.dist-info/entry_points.txt
ytdlp_gui-1.0.1.dist-info/top_level.txt
ytdlp_gui-1.0.1.dist-info/RECORD
