Metadata-Version: 2.4
Name: ytdlp-gui
Version: 1.0.1
Summary: A beautiful GUI for YT-DLP using Flet
Requires-Python: >=3.12.5
License-File: LICENSE
Requires-Dist: flet[all]>=0.27.6
Requires-Dist: yt-dlp>=2025.3.31
Dynamic: license-file
